{"cameraMode":{"drawMode":0,"name":"Shaded","section":"Shading Mode"},"sceneLighting":true,"audioPlay":false,"sceneViewState":{"m_AlwaysRefresh":false,"showFog":true,"showSkybox":true,"showFlares":true,"showImageEffects":true,"showParticleSystems":true,"showVisualEffectGraphs":true,"m_FxEnabled":true},"in2DMode":false,"pivot":{"x":-4.801538944244385,"y":-39.88808059692383,"z":42.87091827392578},"rotation":{"x":0.45138147473335268,"y":-0.0002811197191476822,"z":0.00015521841123700142,"w":0.8923371434211731},"size":51.29783630371094,"orthographic":false}